gprob/__init__.py
gprob/arrayops.py
gprob/fft.py
gprob/func.py
gprob/latent.py
gprob/linalg.py
gprob/maps.py
gprob/normal_.py
gprob/sparse.py
gprob/external/__init__.py
gprob/external/einsubs.py
gprob-1.0.1.dist-info/LICENSE
gprob-1.0.1.dist-info/METADATA
gprob-1.0.1.dist-info/WHEEL
gprob-1.0.1.dist-info/top_level.txt
gprob-1.0.1.dist-info/RECORD
