Metadata-Version: 2.1
Name: gprob
Version: 1.0.1
Summary: Probabilistic programming with arrays of Gaussian variables.
Author-email: Sergey Fedorov <fedorov.s.a@outlook.com>
License: MIT License
Project-URL: Source, https://github.com/SAFedorov/gprob
Keywords: Gaussian distribution,Noise,Random variables,Stochastic processes,Gaussian processes,Probabilistic programming,Python,Numpy,Scipy
Classifier: Intended Audience :: Science/Research
Classifier: License :: OSI Approved :: MIT License
Classifier: Programming Language :: Python
Classifier: Operating System :: OS Independent
Requires-Python: >=3.9
License-File: LICENSE
Requires-Dist: numpy >=1.25
Requires-Dist: scipy
